schema_tools/__init__.py
schema_tools/ast.py
schema_tools/json.py
schema_tools/mapping.py
schema_tools/utils.py
schema_tools/yaml.py
schema_tools/schema/__init__.py
schema_tools/schema/json.py
schema_tools/schema/swagger.py
schema_tools-0.0.19.dist-info/LICENSE.txt
schema_tools-0.0.19.dist-info/METADATA
schema_tools-0.0.19.dist-info/WHEEL
schema_tools-0.0.19.dist-info/top_level.txt
schema_tools-0.0.19.dist-info/RECORD
