Metadata-Version: 2.1
Name: schema-tools
Version: 0.0.19
Summary: Collection of tools to parse, query, map,... Json/Yaml schemas
Home-page: https://github.com/christophevg/schema-tools
Author: Christophe VG
License: MIT
Keywords: json yaml schema tools
Platform: UNKNOWN
Classifier: Development Status :: 3 - Alpha
Classifier: Intended Audience :: Developers
Classifier: Programming Language :: Python
Classifier: Programming Language :: Python :: 3.7
Classifier: Environment :: Console
Classifier: License :: OSI Approved :: MIT License
Classifier: Topic :: Software Development
Requires-Dist: json-cfg
Requires-Dist: pyyaml
Requires-Dist: requests
Requires-Dist: requests-file
